dc_ci/__init__.py
dc_ci/ci1.py
dc_ci/ci1.txt
dc_ci/ci2.py
dc_ci/ci2.txt
dc_ci/ci3.py
dc_ci/ci3.txt
dc_ci/ci4.py
dc_ci/ci4.txt
dc_ci/ci5.py
dc_ci/ci5.txt
dc_ci/dc1.py
dc_ci/dc1.txt
dc_ci/dc2.py
dc_ci/dc2.txt
dc_ci/dc3.py
dc_ci/dc3.txt
dc_ci/dc4.py
dc_ci/dc4.txt
dc_ci/dc5.py
dc_ci/dc5.txt
dc_ci-0.1.0.dist-info/METADATA
dc_ci-0.1.0.dist-info/WHEEL
dc_ci-0.1.0.dist-info/top_level.txt
dc_ci-0.1.0.dist-info/RECORD
