Metadata-Version: 2.1
Name: dc-ci
Version: 0.1.0
Summary: DC CI importable module with multiple files
Home-page: UNKNOWN
Author: Your Name
License: UNKNOWN
Platform: UNKNOWN
